{
  "name": "OrderFeature",
  "relations": {
  },
  "properties": {
    "featureCode": {
      "type": "string",
      "required": false,
      "description": "Mã tính chất đơn",
      "example": "BUYING"
    },
    "featureName": {
      "type": "string",
      "required": false,
      "description": "Tên tính chất đơn",
      "example": "Mua hàng"
    },
    "groupCode": {
      "type": "string",
      "required": false,
      "description": "Mã nhóm của tính chất đơn",
      "example": "INTERNATIONAL"
    },
    "groupName": {
      "type": "string",
      "required": false,
      "description": "Tên nhóm của tính chất đơn",
      "example": "Vận chuyển quốc tế"
    }
  }
}